datacard/__init__.py
datacard/_version.py
datacard/hello.py
datacard-0.0.0.dist-info/METADATA
datacard-0.0.0.dist-info/WHEEL
datacard-0.0.0.dist-info/top_level.txt
datacard-0.0.0.dist-info/RECORD
