Metadata-Version: 2.1
Name: datacard
Version: 0.0.0
Summary: Generate a report card for your data.
Home-page: https://mindfoundry.ai
Author: Mind Foundry Ltd
Author-email: tim.staley@mindfoundry.ai
License: MIT
Platform: UNKNOWN
Classifier: License :: OSI Approved :: MIT License
Classifier: Programming Language :: Python :: 3.6
Classifier: Programming Language :: Python :: 3.7
Classifier: Topic :: Scientific/Engineering :: Information Analysis
Provides-Extra: all
Requires-Dist: check-manifest; extra == 'all'
Requires-Dist: isort; extra == 'all'
Requires-Dist: yapf; extra == 'all'
Requires-Dist: jupyter; extra == 'all'
Requires-Dist: matplotlib; extra == 'all'
Requires-Dist: ipykernel; extra == 'all'
Requires-Dist: sphinx-gallery; extra == 'all'
Requires-Dist: sphinx; extra == 'all'
Requires-Dist: pytest; extra == 'all'
Requires-Dist: coverage; extra == 'all'
Requires-Dist: mypy; extra == 'all'
Requires-Dist: pylint; extra == 'all'
Requires-Dist: pillow; extra == 'all'
Provides-Extra: dev
Requires-Dist: check-manifest; extra == 'dev'
Requires-Dist: coverage; extra == 'dev'
Requires-Dist: isort; extra == 'dev'
Requires-Dist: mypy; extra == 'dev'
Requires-Dist: pylint; extra == 'dev'
Requires-Dist: pytest; extra == 'dev'
Requires-Dist: yapf; extra == 'dev'
Provides-Extra: docs
Requires-Dist: ipykernel; extra == 'docs'
Requires-Dist: jupyter; extra == 'docs'
Requires-Dist: matplotlib; extra == 'docs'
Requires-Dist: pillow; extra == 'docs'
Requires-Dist: sphinx; extra == 'docs'
Requires-Dist: sphinx-gallery; extra == 'docs'
